[
	{
		"gameEntity": {
			"name": "Ring Mail",
			"description": "",
			"referenceURL": "https://dnd5e.fandom.com/wiki/Armor_and_Shields#Heavy_Armor",
			"modify": {
				"base" : "14",
				"modifyField" : "ARMOR_AC",
				"fieldsIModify" : ["CHARACTER_AC"]
			}
		},
		"stealth": false,
		"equipmentType": "HEAVY_ARMOR",
		"donTime" : {
			"amount" : "10",
			"timeUnit": "MINUTE"
		},
		"doffTime" : {
			"amount" : "10",
			"timeUnit": "MINUTE"
		},
		"weightInLbs": "40",
		"valueInGold": "75"
	}
]
